{"cameraMode":{"drawMode":0,"name":"Shaded","section":"Shading Mode"},"sceneLighting":false,"audioPlay":false,"sceneViewState":{"m_AlwaysRefresh":false,"showFog":true,"showSkybox":false,"showFlares":true,"showImageEffects":true,"showParticleSystems":true,"showVisualEffectGraphs":true,"m_FxEnabled":true},"in2DMode":false,"pivot":{"x":-0.06072688102722168,"y":0.3353339433670044,"z":0.12191897630691529},"rotation":{"x":-0.1451774686574936,"y":0.6569862365722656,"z":-0.13099561631679536,"w":-0.7281050682067871},"size":0.3692401647567749,"orthographic":false}